django_liveview-2.1.9.dist-info/licenses/LICENSE
liveview/__init__.py
liveview/apps.py
liveview/connections.py
liveview/consumers.py
liveview/decorators.py
liveview/routing.py
liveview/management/__init__.py
liveview/management/commands/__init__.py
liveview/static/liveview/liveview.js
liveview/static/liveview/liveview.js.map
liveview/static/liveview/liveview.min.js
liveview/templatetags/__init__.py
liveview/templatetags/liveview.py
django_liveview-2.1.9.dist-info/METADATA
django_liveview-2.1.9.dist-info/WHEEL
django_liveview-2.1.9.dist-info/top_level.txt
django_liveview-2.1.9.dist-info/RECORD
