Metadata-Version: 2.4
Name: django-liveview
Version: 2.1.9
Summary: Real-time server-rendered interfaces for Django using WebSockets
Home-page: https://github.com/tanrax/django-liveview
Author: Andros Fenollosa
Author-email: Andros Fenollosa <andros@fenollosa.email>
License: MIT
Project-URL: Homepage, https://django-liveview.andros.dev/
Project-URL: Documentation, https://django-liveview.andros.dev/
Project-URL: Repository, https://github.com/Django-LiveView/liveview
Project-URL: Issues, https://github.com/Django-LiveView/liveview/issues
Keywords: django,liveview,websockets,realtime,stimulus,channels
Classifier: Development Status :: 5 - Production/Stable
Classifier: Environment :: Web Environment
Classifier: Framework :: Django
Classifier: Framework :: Django :: 4.2
Classifier: Framework :: Django :: 5.0
Classifier: Framework :: Django :: 5.1
Classifier: Framework :: Django :: 5.2
Classifier: Intended Audience :: Developers
Classifier: License :: OSI Approved :: MIT License
Classifier: Operating System :: OS Independent
Classifier: Programming Language :: Python
Classifier: Programming Language :: Python :: 3
Classifier: Programming Language :: Python :: 3.10
Classifier: Programming Language :: Python :: 3.11
Classifier: Programming Language :: Python :: 3.12
Classifier: Programming Language :: JavaScript
Classifier: Topic :: Internet :: WWW/HTTP
Classifier: Topic :: Internet :: WWW/HTTP :: Dynamic Content
Classifier: Topic :: Software Development :: Libraries :: Application Frameworks
Classifier: Topic :: Software Development :: Libraries :: Python Modules
Requires-Python: >=3.10
License-File: LICENSE
Requires-Dist: django>=4.2
Requires-Dist: channels>=4.0.0
Requires-Dist: channels-redis>=4.0.0
Provides-Extra: dev
Requires-Dist: pytest>=7.0.0; extra == "dev"
Requires-Dist: pytest-django>=4.5.0; extra == "dev"
Requires-Dist: pytest-asyncio>=0.21.0; extra == "dev"
Requires-Dist: black>=23.0.0; extra == "dev"
Requires-Dist: ruff>=0.1.0; extra == "dev"
Requires-Dist: mypy>=1.0.0; extra == "dev"
Dynamic: author
Dynamic: home-page
Dynamic: license-file
Dynamic: requires-python
